monsterpianotransformer/README.md
monsterpianotransformer/TMIDIX.py
monsterpianotransformer/__init__.py
monsterpianotransformer/midi_processors.py
monsterpianotransformer/midi_to_colab_audio.py
monsterpianotransformer/model_loader.py
monsterpianotransformer/models.py
monsterpianotransformer/monsterpianotransformer.py
monsterpianotransformer/sample_midis.py
monsterpianotransformer/x_transformer_1_23_2.py
monsterpianotransformer/artwork/Monster-Piano-Transformer-Artwork-1.jpg
monsterpianotransformer/artwork/Monster-Piano-Transformer-Artwork-2.jpg
monsterpianotransformer/artwork/README.md
monsterpianotransformer/artwork/__init__.py
monsterpianotransformer/examples/README.md
monsterpianotransformer/examples/__init__.py
monsterpianotransformer/gradio/README.md
monsterpianotransformer/gradio/TMIDIX.py
monsterpianotransformer/gradio/__init__.py
monsterpianotransformer/gradio/__main__.py
monsterpianotransformer/gradio/app.py
monsterpianotransformer/gradio/app_full.py
monsterpianotransformer/gradio/midi_to_colab_audio.py
monsterpianotransformer/gradio/packages.txt
monsterpianotransformer/gradio/requirements.txt
monsterpianotransformer/gradio/x_transformer_1_23_2.py
monsterpianotransformer/output_samples/The Ballad of Camelot - Supervised Continuation.mid
monsterpianotransformer/output_samples/The Ultimate 200 Anime Songs Piano Medley - Long Chords Texturing.mid
monsterpianotransformer/output_samples/__init__.py
monsterpianotransformer/seed_midis/Monster-Piano-Transformer-MI-Seed-1.mid
monsterpianotransformer/seed_midis/Monster-Piano-Transformer-MI-Seed-2.mid
monsterpianotransformer/seed_midis/Monster-Piano-Transformer-MI-Seed-3.mid
monsterpianotransformer/seed_midis/Monster-Piano-Transformer-MI-Seed-4.mid
monsterpianotransformer/seed_midis/Monster-Piano-Transformer-MI-Seed-5.mid
monsterpianotransformer/seed_midis/Monster-Piano-Transformer-MI-Seed-6.mid
monsterpianotransformer/seed_midis/Monster-Piano-Transformer-Piano-Seed-1.mid
monsterpianotransformer-25.1.92.dist-info/LICENSE
monsterpianotransformer-25.1.92.dist-info/METADATA
monsterpianotransformer-25.1.92.dist-info/WHEEL
monsterpianotransformer-25.1.92.dist-info/entry_points.txt
monsterpianotransformer-25.1.92.dist-info/top_level.txt
monsterpianotransformer-25.1.92.dist-info/RECORD
