Metadata-Version: 2.2
Name: monsterpianotransformer
Version: 25.1.92
Summary: Ultra-fast and very well fitted solo Piano music transformer
Home-page: https://github.com/asigalov61/monsterpianotransformer
Author: Alex Lev
Author-email: Alex Lev <alexlev61@proton.me>
Maintainer-email: Alex Lev <alexlev61@proton.me>
License: Apache Software License 2.0
Project-URL: Homepage, https://github.com/asigalov61/monsterpianotransformer
Project-URL: SoundCloud, https://soundcloud.com/aleksandr-sigalov-61/sets/monster-piano-transformer
Project-URL: Samples, https://github.com/asigalov61/monsterpianotransformer/tree/main/monsterpianotransformer/output_samples
Project-URL: Examples, https://github.com/asigalov61/monsterpianotransformer/tree/main/monsterpianotransformer/examples
Project-URL: Documentation, https://github.com/asigalov61/monsterpianotransformer
Project-URL: Issues, https://github.com/asigalov61/monsterpianotransformer/issues
Project-URL: Discussions, https://github.com/asigalov61/monsterpianotransformer/discussions
Project-URL: Models, https://huggingface.co/asigalov61/Monster-Piano-Transformer
Project-URL: Demo, https://huggingface.co/spaces/asigalov61/Monster-Piano-Transformer
Keywords: MIDI,music,music ai,music transformer,artificial instelligence,piano transformer
Classifier: Development Status :: 5 - Production/Stable
Classifier: Intended Audience :: Science/Research
Classifier: Topic :: Multimedia :: Sound/Audio :: MIDI
Classifier: License :: OSI Approved :: Apache Software License
Classifier: Operating System :: OS Independent
Classifier: Programming Language :: Python :: 3.6
Classifier: Programming Language :: Python :: 3.7
Classifier: Programming Language :: Python :: 3.8
Classifier: Programming Language :: Python :: 3.9
Classifier: Programming Language :: Python :: 3.10
Classifier: Programming Language :: Python :: 3.11
Classifier: Programming Language :: Python :: 3.12
Requires-Python: >=3.6
License-File: LICENSE
Requires-Dist: tqdm
Requires-Dist: ipywidgets
Requires-Dist: matplotlib
Requires-Dist: numpy
Requires-Dist: scikit-learn
Requires-Dist: torch
Requires-Dist: einops
Requires-Dist: torch-summary
Requires-Dist: hf-transfer
Requires-Dist: huggingface_hub
Requires-Dist: gradio
Dynamic: author
Dynamic: home-page
Dynamic: requires-python
